if_license_plates_could_talk/__init__.py
if_license_plates_could_talk/__main__.py
if_license_plates_could_talk/app.py
if_license_plates_could_talk/prep_data.py
if_license_plates_could_talk/setup_db.py
if_license_plates_could_talk/data/__init__.py
if_license_plates_could_talk/data/border_vicinity.py
if_license_plates_could_talk/data/crime.py
if_license_plates_could_talk/data/database.py
if_license_plates_could_talk/data/education.py
if_license_plates_could_talk/data/election.py
if_license_plates_could_talk/data/household.py
if_license_plates_could_talk/data/income.py
if_license_plates_could_talk/data/license_plate.py
if_license_plates_could_talk/data/population.py
if_license_plates_could_talk/data/regions.py
if_license_plates_could_talk/data/utils.py
if_license_plates_could_talk/data/data_files/.DS_Store
if_license_plates_could_talk/data/data_files/processed/.DS_Store
if_license_plates_could_talk/data/data_files/processed/data.csv
if_license_plates_could_talk/data/data_files/processed/data_desc.xlsx
if_license_plates_could_talk/data/data_files/processed/merged.csv
if_license_plates_could_talk/data/data_files/processed/border_vicinity/border_vicinity.csv
if_license_plates_could_talk/data/data_files/processed/crime/.DS_Store
if_license_plates_could_talk/data/data_files/processed/crime/categories.csv
if_license_plates_could_talk/data/data_files/processed/crime/crime.csv
if_license_plates_could_talk/data/data_files/processed/education/education.csv
if_license_plates_could_talk/data/data_files/processed/election/election.csv
if_license_plates_could_talk/data/data_files/processed/election/parties.csv
if_license_plates_could_talk/data/data_files/processed/household/household.csv
if_license_plates_could_talk/data/data_files/processed/income/.DS_Store
if_license_plates_could_talk/data/data_files/processed/income/income.csv
if_license_plates_could_talk/data/data_files/processed/license_plate/license_plate.csv
IF_LICENSE_PLATES_COULD_TALK-0.0.1.dist-info/METADATA
IF_LICENSE_PLATES_COULD_TALK-0.0.1.dist-info/WHEEL
IF_LICENSE_PLATES_COULD_TALK-0.0.1.dist-info/top_level.txt
IF_LICENSE_PLATES_COULD_TALK-0.0.1.dist-info/RECORD
