Metadata-Version: 2.1
Name: IF-LICENSE-PLATES-COULD-TALK
Version: 0.0.1
Summary: German license plates geographical information is used to link them to income and crime.
Home-page: https://github.com/dullibri/if_license_plates_could_talk
Author: Moritz Hartlieb
Author-email: moritz-hartlieb@web.de
License: UNKNOWN
Project-URL: Bug Tracker, https://github.com/dullibri/if_license_plates_could_talk/issues
Platform: UNKNOWN
Classifier: Programming Language :: Python :: 3
Classifier: License :: OSI Approved :: MIT License
Classifier: Operating System :: OS Independent
Requires-Python: >=3.6
Requires-Dist: bs4
Requires-Dist: dash
Requires-Dist: dash-bootstrap-components
Requires-Dist: dash-core-components
Requires-Dist: dash-html-components
Requires-Dist: geopandas
Requires-Dist: matplotlib
Requires-Dist: numpy
Requires-Dist: openpyxl
Requires-Dist: pandas
Requires-Dist: plotly
Requires-Dist: pyproj
Requires-Dist: requests
Requires-Dist: scikit-learn
Requires-Dist: scipy
Requires-Dist: statsmodels
Requires-Dist: xlrd
Requires-Dist: geopy
Requires-Dist: gunicorn
